{"BTC/AUD":{"tierBased":false,"percentage":true,"taker":0.005,"maker":0.005,"id":"Xbt/Aud","symbol":"BTC/AUD","base":"BTC","quote":"AUD","baseId":"Xbt","quoteId":"Aud","info":"Xbt/Aud"},"BTC/USD":{"tierBased":false,"percentage":true,"taker":0.005,"maker":0.005,"id":"Xbt/Usd","symbol":"BTC/USD","base":"BTC","quote":"USD","baseId":"Xbt","quoteId":"Usd","info":"Xbt/Usd"},"BTC/NZD":{"tierBased":false,"percentage":true,"taker":0.005,"maker":0.005,"id":"Xbt/Nzd","symbol":"BTC/NZD","base":"BTC","quote":"NZD","baseId":"Xbt","quoteId":"Nzd","info":"Xbt/Nzd"},"XRP/AUD":{"tierBased":false,"percentage":true,"taker":0.005,"maker":0.005,"id":"Xrp/Aud","symbol":"XRP/AUD","base":"XRP","quote":"AUD","baseId":"Xrp","quoteId":"Aud","info":"Xrp/Aud"},"XRP/USD":{"tierBased":false,"percentage":true,"taker":0.005,"maker":0.005,"id":"Xrp/Usd","symbol":"XRP/USD","base":"XRP","quote":"USD","baseId":"Xrp","quoteId":"Usd","info":"Xrp/Usd"},"XRP/NZD":{"tierBased":false,"percentage":true,"taker":0.005,"maker":0.005,"id":"Xrp/Nzd","symbol":"XRP/NZD","base":"XRP","quote":"NZD","baseId":"Xrp","quoteId":"Nzd","info":"Xrp/Nzd"},"ETH/AUD":{"tierBased":false,"percentage":true,"taker":0.005,"maker":0.005,"id":"Eth/Aud","symbol":"ETH/AUD","base":"ETH","quote":"AUD","baseId":"Eth","quoteId":"Aud","info":"Eth/Aud"},"ETH/USD":{"tierBased":false,"percentage":true,"taker":0.005,"maker":0.005,"id":"Eth/Usd","symbol":"ETH/USD","base":"ETH","quote":"USD","baseId":"Eth","quoteId":"Usd","info":"Eth/Usd"},"ETH/NZD":{"tierBased":false,"percentage":true,"taker":0.005,"maker":0.005,"id":"Eth/Nzd","symbol":"ETH/NZD","base":"ETH","quote":"NZD","baseId":"Eth","quoteId":"Nzd","info":"Eth/Nzd"},"BCH/AUD":{"tierBased":false,"percentage":true,"taker":0.005,"maker":0.005,"id":"Bch/Aud","symbol":"BCH/AUD","base":"BCH","quote":"AUD","baseId":"Bch","quoteId":"Aud","info":"Bch/Aud"},"BCH/USD":{"tierBased":false,"percentage":true,"taker":0.005,"maker":0.005,"id":"Bch/Usd","symbol":"BCH/USD","base":"BCH","quote":"USD","baseId":"Bch","quoteId":"Usd","info":"Bch/Usd"},"BCH/NZD":{"tierBased":false,"percentage":true,"taker":0.005,"maker":0.005,"id":"Bch/Nzd","symbol":"BCH/NZD","base":"BCH","quote":"NZD","baseId":"Bch","quoteId":"Nzd","info":"Bch/Nzd"},"LTC/AUD":{"tierBased":false,"percentage":true,"taker":0.005,"maker":0.005,"id":"Ltc/Aud","symbol":"LTC/AUD","base":"LTC","quote":"AUD","baseId":"Ltc","quoteId":"Aud","info":"Ltc/Aud"},"LTC/USD":{"tierBased":false,"percentage":true,"taker":0.005,"maker":0.005,"id":"Ltc/Usd","symbol":"LTC/USD","base":"LTC","quote":"USD","baseId":"Ltc","quoteId":"Usd","info":"Ltc/Usd"},"LTC/NZD":{"tierBased":false,"percentage":true,"taker":0.005,"maker":0.005,"id":"Ltc/Nzd","symbol":"LTC/NZD","base":"LTC","quote":"NZD","baseId":"Ltc","quoteId":"Nzd","info":"Ltc/Nzd"},"PLA/AUD":{"tierBased":false,"percentage":true,"taker":0.005,"maker":0.005,"id":"Pla/Aud","symbol":"PLA/AUD","base":"PLA","quote":"AUD","baseId":"Pla","quoteId":"Aud","info":"Pla/Aud"},"PLA/USD":{"tierBased":false,"percentage":true,"taker":0.005,"maker":0.005,"id":"Pla/Usd","symbol":"PLA/USD","base":"PLA","quote":"USD","baseId":"Pla","quoteId":"Usd","info":"Pla/Usd"},"PLA/NZD":{"tierBased":false,"percentage":true,"taker":0.005,"maker":0.005,"id":"Pla/Nzd","symbol":"PLA/NZD","base":"PLA","quote":"NZD","baseId":"Pla","quoteId":"Nzd","info":"Pla/Nzd"},"OMG/AUD":{"tierBased":false,"percentage":true,"taker":0.005,"maker":0.005,"id":"Omg/Aud","symbol":"OMG/AUD","base":"OMG","quote":"AUD","baseId":"Omg","quoteId":"Aud","info":"Omg/Aud"},"OMG/USD":{"tierBased":false,"percentage":true,"taker":0.005,"maker":0.005,"id":"Omg/Usd","symbol":"OMG/USD","base":"OMG","quote":"USD","baseId":"Omg","quoteId":"Usd","info":"Omg/Usd"},"OMG/NZD":{"tierBased":false,"percentage":true,"taker":0.005,"maker":0.005,"id":"Omg/Nzd","symbol":"OMG/NZD","base":"OMG","quote":"NZD","baseId":"Omg","quoteId":"Nzd","info":"Omg/Nzd"},"ZRX/AUD":{"tierBased":false,"percentage":true,"taker":0.005,"maker":0.005,"id":"Zrx/Aud","symbol":"ZRX/AUD","base":"ZRX","quote":"AUD","baseId":"Zrx","quoteId":"Aud","info":"Zrx/Aud"},"ZRX/USD":{"tierBased":false,"percentage":true,"taker":0.005,"maker":0.005,"id":"Zrx/Usd","symbol":"ZRX/USD","base":"ZRX","quote":"USD","baseId":"Zrx","quoteId":"Usd","info":"Zrx/Usd"},"ZRX/NZD":{"tierBased":false,"percentage":true,"taker":0.005,"maker":0.005,"id":"Zrx/Nzd","symbol":"ZRX/NZD","base":"ZRX","quote":"NZD","baseId":"Zrx","quoteId":"Nzd","info":"Zrx/Nzd"}}